{"cameraMode":{"drawMode":0,"name":"Shaded","section":"Shading Mode"},"sceneLighting":true,"audioPlay":false,"sceneViewState":{"m_AlwaysRefresh":false,"showFog":true,"showSkybox":true,"showFlares":true,"showImageEffects":true,"showParticleSystems":true,"showVisualEffectGraphs":true,"m_FxEnabled":true},"in2DMode":false,"pivot":{"x":27.133607864379884,"y":30.739646911621095,"z":31.682296752929689},"rotation":{"x":-0.22030548751354218,"y":0.24759042263031007,"z":-0.057921744883060458,"w":-0.9417079091072083},"size":5.133212566375732,"orthographic":false}